{
  "source": "artifacts\\roms\\BASELINE_TND64_Expanded_direct_from_stock.z64",
  "target": "artifacts\\generated\\game_h460_top10_stock_dossier_tlbpages58_007label_current.z64",
  "source_md5": "1ee22dd1d70443f5e4766d4238756949",
  "target_md5": "25cd6b104b4cbdf3b2cdf4e1d02354da",
  "source_sha256": "ba5e040de292d7d192d0f88f12dcf4cbde7eb4d643926830d7d77557bf6df502",
  "target_sha256": "f3b3baf7e2064d952d8eba9b1d71e2204dea4ee2c590891f4963c0bf8abf3fa1",
  "note": "TND6480i TLB page-count 58 007-label current diagnostic",
  "patch": "artifacts\\generated\\TND6480i_game_h460_top10_stock_dossier_tlbpages58_007label_from_baseline_tnd.bps",
  "patch_bytes": 179152,
  "patch_md5": "7e576a51f9467c7a29374dfb7d65221a",
  "patch_sha256": "3e503a81d494289cdc30b758177e88ce9f9fb43438c9ab36e340c33026826b17",
  "source_bytes": 16777216,
  "target_bytes": 16885376,
  "source_crc32": "321C1845",
  "target_crc32": "21C0D916",
  "patch_crc32": "DF04B61A",
  "verified": true,
  "action_count": 400,
  "source_read_bytes": 16707325,
  "target_read_bytes": 178051,
  "actions_preview": [
    {
      "type": "SourceRead",
      "offset": 0,
      "length": 16
    },
    {
      "type": "TargetRead",
      "offset": 16,
      "length": 8
    },
    {
      "type": "SourceRead",
      "offset": 24,
      "length": 9731
    },
    {
      "type": "TargetRead",
      "offset": 9755,
      "length": 1
    },
    {
      "type": "SourceRead",
      "offset": 9756,
      "length": 5744
    },
    {
      "type": "TargetRead",
      "offset": 15500,
      "length": 12
    },
    {
      "type": "SourceRead",
      "offset": 15512,
      "length": 153
    },
    {
      "type": "TargetRead",
      "offset": 15665,
      "length": 59
    },
    {
      "type": "SourceRead",
      "offset": 15724,
      "length": 1715
    },
    {
      "type": "TargetRead",
      "offset": 17439,
      "length": 1
    },
    {
      "type": "SourceRead",
      "offset": 17440,
      "length": 661
    },
    {
      "type": "TargetRead",
      "offset": 18101,
      "length": 59
    },
    {
      "type": "SourceRead",
      "offset": 18160,
      "length": 7831
    },
    {
      "type": "TargetRead",
      "offset": 25991,
      "length": 49
    },
    {
      "type": "SourceRead",
      "offset": 26040,
      "length": 40742
    },
    {
      "type": "TargetRead",
      "offset": 66782,
      "length": 1
    },
    {
      "type": "SourceRead",
      "offset": 66783,
      "length": 38041
    },
    {
      "type": "TargetRead",
      "offset": 104824,
      "length": 16
    },
    {
      "type": "SourceRead",
      "offset": 104840,
      "length": 44
    },
    {
      "type": "TargetRead",
      "offset": 104884,
      "length": 3
    }
  ]
}
